pref/__init__.py
pref/__version__.py
pref/pref.py
pref/py.typed
pref-0.2.0.dist-info/LICENSE
pref-0.2.0.dist-info/LICENSE.txt
pref-0.2.0.dist-info/METADATA
pref-0.2.0.dist-info/WHEEL
pref-0.2.0.dist-info/top_level.txt
pref-0.2.0.dist-info/RECORD
