Metadata-Version: 2.1
Name: pref
Version: 0.2.0
Summary: persistent preferences store to local sqlite
Home-page: https://github.com/jamesabel/pref
Download-URL: https://github.com/jamesabel/pref
Author: abel
Author-email: j@abel.co
License: MIT
Keywords: local,preferences,sqlite
License-File: LICENSE
License-File: LICENSE.txt
Requires-Dist: sqlitedict
Requires-Dist: attrs
Requires-Dist: appdirs
